ssrviz/__init__.py
ssrviz/setup_fx.py
ssrviz/setup_fx_win.py
ssrviz/ssrviz.py
ssrviz/ssrviz_draw.py
ssrviz/ssrviz_sub.py
ssrviz/add_on/__init__.py
ssrviz/add_on/add_pdb2alignment.py
ssrviz/prediction_rules/__init__.py
ssrviz/prediction_rules/csv_builder.py
ssrviz/prediction_rules/domain_extractor.py
ssrviz/prediction_rules/main_pred.py
ssrviz/prediction_rules/prediction_rules.py
ssrviz/prediction_rules/pssm_func.py
ssrviz/prediction_rules/pssm_func_test.py
ssrviz/prediction_rules/sequence_translations.py
ssrviz/prediction_rules/basic/__init__.py
ssrviz/prediction_rules/basic/basic.py
ssrviz/prediction_rules/basic/file_conversion.py
ssrviz/prediction_rules/lib/__init__.py
ssrviz/prediction_rules/lib/mpl_strong_colors.py
ssrviz/prediction_rules/lib/property_AS_matrix.py
ssrviz-1.0.1.dist-info/METADATA
ssrviz-1.0.1.dist-info/RECORD
ssrviz-1.0.1.dist-info/WHEEL
ssrviz-1.0.1.dist-info/entry_points.txt
ssrviz-1.0.1.dist-info/top_level.txt
