Metadata-Version: 2.1
Name: ssrviz
Version: 1.0.1
Summary: Protein subfamily specific residue (SSR) detection and visualization toolbox
Home-page: http://phabi.de/
Author: Paul Zierep
Author-email: Paul.Zierep@googlemail.com
License: UNKNOWN
Platform: UNKNOWN
Requires-Dist: biopython (>=1.70)
Requires-Dist: numpy (>=1.14.3)
Requires-Dist: scipy (>=1.1.0)
Requires-Dist: matplotlib (>=2.2.2)
Requires-Dist: natsort (>=5.3.0)
Requires-Dist: Gooey (==1.0.0)
Requires-Dist: pandas (>=0.21.0)
